<?xml version="1.0"?>
<Workbook xmlns="urn:schemas-microsoft-com:office:spreadsheet"
 xmlns:o="urn:schemas-microsoft-com:office:office"
 xmlns:x="urn:schemas-microsoft-com:office:excel"
 xmlns:ss="urn:schemas-microsoft-com:office:spreadsheet"
 xmlns:html="http://www.w3.org/TR/REC-html40">
 <DocumentProperties xmlns="urn:schemas-microsoft-com:office:office">
  <作者>1528-01</作者>
  <LastAuthor>gz fs</LastAuthor>
  <创建>2013-08-23T06:37:21Z</创建>
  <上次保存>2013-08-25T09:31:24Z</上次保存>
  <版本>14.0</版本>
 </DocumentProperties>
 <OfficeDocumentSettings xmlns="urn:schemas-microsoft-com:office:office">
  <AllowPNG/>
 </OfficeDocumentSettings>
 <ExcelWorkbook xmlns="urn:schemas-microsoft-com:office:excel">
  <WindowHeight>10380</WindowHeight>
  <WindowWidth>25600</WindowWidth>
  <WindowTopX>260</WindowTopX>
  <WindowTopY>0</WindowTopY>
  <TabRatio>600</TabRatio>
  <ProtectStructure>False</ProtectStructure>
  <ProtectWindows>False</ProtectWindows>
 </ExcelWorkbook>
 <Styles>
  <Style ss:ID="Default" ss:Name="Normal">
   <Alignment ss:Vertical="Center"/>
   <Borders/>
   <Font ss:FontName="Calibri" x:CharSet="134" x:Family="Swiss" ss:Size="11"
    ss:Color="#000000"/>
   <Interior/>
   <NumberFormat/>
   <Protection/>
  </Style>
  <Style ss:ID="s16" ss:Name="超级链接">
   <Font ss:FontName="Calibri" x:CharSet="134" x:Family="Swiss" ss:Size="11"
    ss:Color="#0000D4" ss:Underline="Single"/>
  </Style>
  <Style ss:ID="s17">
   <Alignment ss:Horizontal="Center" ss:Vertical="Center" ss:WrapText="1"/>
  </Style>
  <Style ss:ID="s18" ss:Parent="s16">
   <Alignment ss:Horizontal="Center" ss:Vertical="Center" ss:WrapText="1"/>
  </Style>
  <Style ss:ID="s19">
   <Alignment ss:Horizontal="Center" ss:Vertical="Center"/>
   <Font ss:FontName="宋体" x:CharSet="134" x:Family="Modern" ss:Size="11"
    ss:Color="#000000"/>
  </Style>
  <Style ss:ID="s20">
   <Alignment ss:Horizontal="Center" ss:Vertical="Center"/>
   <Font ss:FontName="Tahoma" x:Family="Swiss" ss:Size="11" ss:Color="#000000"/>
  </Style>
  <Style ss:ID="s21">
   <Alignment ss:Horizontal="Center" ss:Vertical="Center" ss:WrapText="1"/>
   <Interior ss:Color="#A2BD90" ss:Pattern="Solid"/>
  </Style>
 </Styles>
 <Worksheet ss:Name="Sheet1">
  <Table ss:ExpandedColumnCount="16" ss:ExpandedRowCount="287" x:FullColumns="1"
   x:FullRows="1" ss:StyleID="s17" ss:DefaultColumnWidth="144"
   ss:DefaultRowHeight="12">
   <Column ss:StyleID="s17" ss:AutoFitWidth="0" ss:Width="74" ss:Span="2"/>
   <Column ss:Index="4" ss:StyleID="s17" ss:AutoFitWidth="0" ss:Width="101"/>
   <Column ss:StyleID="s17" ss:AutoFitWidth="0" ss:Width="58"/>
   <Column ss:StyleID="s17" ss:AutoFitWidth="0" ss:Width="35"/>
   <Column ss:StyleID="s17" ss:AutoFitWidth="0" ss:Width="158"/>
   <Column ss:StyleID="s17" ss:AutoFitWidth="0" ss:Width="153"/>
   <Column ss:Index="10" ss:StyleID="s17" ss:AutoFitWidth="0" ss:Width="239"/>
   <Column ss:StyleID="s17" ss:AutoFitWidth="0" ss:Width="74" ss:Span="1"/>
   <Column ss:Index="13" ss:StyleID="s21" ss:AutoFitWidth="0"/>
   <Column ss:StyleID="s17" ss:AutoFitWidth="0" ss:Width="81" ss:Span="1"/>
   <Row>
    <Cell><Data ss:Type="String">id</Data></Cell>
    <Cell><Data ss:Type="String">模式</Data></Cell>
    <Cell><Data ss:Type="String">素材编号</Data></Cell>
    <Cell><Data ss:Type="String">素材描述</Data></Cell>
    <Cell><Data ss:Type="String">标签</Data></Cell>
    <Cell><Data ss:Type="String">难度</Data></Cell>
    <Cell><Data ss:Type="String">问题</Data></Cell>
    <Cell><Data ss:Type="String">暗示</Data></Cell>
    <Cell><Data ss:Type="String">答案</Data></Cell>
    <Cell><Data ss:Type="String">干扰词</Data></Cell>
    <Cell><Data ss:Type="String">答对图片</Data></Cell>
    <Cell><Data ss:Type="String">图片描述</Data></Cell>
    <Cell><Data ss:Type="String">答对对话</Data></Cell>
    <Cell><Data ss:Type="String">超链接类型</Data></Cell>
    <Cell><Data ss:Type="String">超链接标题</Data></Cell>
    <Cell><Data ss:Type="String">超链接</Data></Cell>
   </Row>
   <Row ss:Height="36">
    <Cell><Data ss:Type="Number">1</Data></Cell>
    <Cell><Data ss:Type="String">画图</Data></Cell>
    <Cell ss:Index="4"><Data ss:Type="String">船（4个烟囱）和冰山</Data></Cell>
    <Cell><Data ss:Type="String">电影</Data></Cell>
    <Cell><Data ss:Type="Number">2</Data></Cell>
    <Cell><Data ss:Type="String">猜一部电影</Data></Cell>
    <Cell><Data ss:Type="String">最惨的事故 最美的爱情</Data></Cell>
    <Cell><Data ss:Type="String">泰坦尼克号$铁达尼克号</Data></Cell>
    <Cell><Data ss:Type="String">超人，安娜，海洋，冰山</Data></Cell>
    <Cell><Data ss:Type="String">/</Data></Cell>
    <Cell><Data ss:Type="String">/</Data></Cell>
    <Cell><Data ss:Type="String">泰坦尼克号沉没背后的的惊天保险诈骗案你知道么？</Data></Cell>
    <Cell><Data ss:Type="String">视频</Data></Cell>
    <Cell><Data ss:Type="String">泰坦尼克号沉没背后的的惊天保险诈骗案</Data></Cell>
    <Cell ss:StyleID="s18" ss:HRef="http://tv.sohu.com/20101228/n278556355.shtml"><Data
      ss:Type="String">http://tv.sohu.com/20101228/n278556355.shtml</Data></Cell>
   </Row>
   <Row ss:Height="48">
    <Cell><Data ss:Type="Number">2</Data></Cell>
    <Cell><Data ss:Type="String">偷听</Data></Cell>
    <Cell ss:Index="4"><Data ss:Type="String">最炫民族风</Data></Cell>
    <Cell><Data ss:Type="String">神曲</Data></Cell>
    <Cell><Data ss:Type="Number">1</Data></Cell>
    <Cell><Data ss:Type="String">这是哪首神曲啊？</Data></Cell>
    <Cell><Data ss:Type="String">那个什么凤凰组合…</Data></Cell>
    <Cell><Data ss:Type="String">最炫民族风</Data></Cell>
    <Cell><Data ss:Type="String">忐忑，国歌，吻别，爱你一万年</Data></Cell>
    <Cell><Data ss:Type="String">mp0001</Data></Cell>
    <Cell><Data ss:Type="String">惊吓的野猪</Data></Cell>
    <Cell><Data ss:Type="String">为了防止野猪来袭，辽阳县八会镇宽厂峪村的村民们放起了最炫民族风，随之野猪闻取逃，神曲果然是神曲。</Data></Cell>
    <Cell><Data ss:Type="String">音乐</Data></Cell>
    <Cell><Data ss:Type="String">最炫民族风试听</Data></Cell>
    <Cell ss:StyleID="s18" ss:HRef="http://music.baidu.com/#/!/song/246301?rate=%E6%99%AE%E9%80%9A%E7%89%88&amp;fm=ald"><Data
      ss:Type="String">http://music.baidu.com/#/!/song/246301?rate=%E6%99%AE%E9%80%9A%E7%89%88&amp;fm=ald</Data></Cell>
   </Row>
   <Row ss:Height="36">
    <Cell><Data ss:Type="Number">3</Data></Cell>
    <Cell><Data ss:Type="String">画图</Data></Cell>
    <Cell ss:Index="4"><Data ss:Type="String">希特勒卡通肖像</Data></Cell>
    <Cell><Data ss:Type="String">历史人物</Data></Cell>
    <Cell><Data ss:Type="Number">2</Data></Cell>
    <Cell><Data ss:Type="String">猜一个人物</Data></Cell>
    <Cell><Data ss:Type="String">他是二战纳粹党首</Data></Cell>
    <Cell><Data ss:Type="String">希特勒</Data></Cell>
    <Cell><Data ss:Type="String">丘吉尔，毛泽东，杰克逊，布什</Data></Cell>
    <Cell><Data ss:Type="String">pp0002</Data></Cell>
    <Cell><Data ss:Type="String">希特勒和外星人</Data></Cell>
    <Cell><Data ss:Type="String">FBI解密：1942年5月2日希特勒首次代表人类和外星人接触！</Data></Cell>
    <Cell><Data ss:Type="String">视频</Data></Cell>
    <Cell><Data ss:Type="String">希特勒的外星魔力狂想</Data></Cell>
    <Cell ss:StyleID="s18" ss:HRef="http://tv.sohu.com/20101227/n278532384.shtml"><Data
      ss:Type="String">http://tv.sohu.com/20101227/n278532384.shtml</Data></Cell>
   </Row>
   <Row ss:Height="84">
    <Cell><Data ss:Type="Number">4</Data></Cell>
    <Cell><Data ss:Type="String">画图</Data></Cell>
    <Cell ss:Index="4"><Data ss:Type="String">毛泽东卡通肖像</Data></Cell>
    <Cell><Data ss:Type="String">历史人物</Data></Cell>
    <Cell><Data ss:Type="Number">2</Data></Cell>
    <Cell><Data ss:Type="String">猜一个人物</Data></Cell>
    <Cell><Data ss:Type="String">他爱吃红烧肉</Data></Cell>
    <Cell><Data ss:Type="String">毛泽东</Data></Cell>
    <Cell><Data ss:Type="String">丘吉尔，希特勒，杰克逊，布什</Data></Cell>
    <Cell ss:Index="13"><Data ss:Type="String">你知道“8341部队”么？毛泽东把自己的警卫团叫“八三四一”部队，而毛泽东刚好活了83岁，前后主政41年。“八三四一”番号与这两个时间吻合，真乃神人啊~喵</Data></Cell>
    <Cell><Data ss:Type="String">新闻</Data></Cell>
    <Cell><Data ss:Type="String">毛泽东与神秘&quot;8341&quot;部队 番号背后藏神秘传说</Data></Cell>
    <Cell ss:StyleID="s18" ss:HRef="http://www.china.com.cn/culture/lishi/2010-05/07/content_19995694.htm"><Data
      ss:Type="String">http://www.china.com.cn/culture/lishi/2010-05/07/content_19995694.htm</Data></Cell>
   </Row>
   <Row ss:Height="48">
    <Cell><Data ss:Type="Number">5</Data></Cell>
    <Cell><Data ss:Type="String">画图</Data></Cell>
    <Cell ss:Index="4"><Data ss:Type="String">一张纸、一支笔，两只手</Data></Cell>
    <Cell><Data ss:Type="String">灵异</Data></Cell>
    <Cell><Data ss:Type="Number">2</Data></Cell>
    <Cell><Data ss:Type="String">猜一种游戏</Data></Cell>
    <Cell><Data ss:Type="String">这是一种通灵游戏</Data></Cell>
    <Cell><Data ss:Type="String">笔仙</Data></Cell>
    <Cell><Data ss:Type="String">碟子，飞碟，幽灵，超人</Data></Cell>
    <Cell><Data ss:Type="String">/</Data></Cell>
    <Cell><Data ss:Type="String">/</Data></Cell>
    <Cell><Data ss:Type="String">两名在校女中学生刘英和李萍相约跳楼，一人当场死亡。应城警方公布身亡女生死因系玩笔仙游戏所致。</Data></Cell>
    <Cell><Data ss:Type="String">新闻</Data></Cell>
    <Cell><Data ss:Type="String">少女玩笔仙入迷途相继轻生</Data></Cell>
    <Cell ss:StyleID="s18" ss:HRef="http://hlj.sina.com.cn/news/s/2013-05-31/101954010.html"><Data
      ss:Type="String">http://hlj.sina.com.cn/news/s/2013-05-31/101954010.html</Data></Cell>
   </Row>
   <Row ss:Height="60">
    <Cell><Data ss:Type="Number">6</Data></Cell>
    <Cell><Data ss:Type="String">画图</Data></Cell>
    <Cell ss:Index="4"><Data ss:Type="String">赵、秦、玉璧</Data></Cell>
    <Cell><Data ss:Type="String">成语</Data></Cell>
    <Cell><Data ss:Type="Number">1</Data></Cell>
    <Cell><Data ss:Type="String">猜一个成语</Data></Cell>
    <Cell><Data ss:Type="String">一块玉璧的故事…</Data></Cell>
    <Cell><Data ss:Type="String">完璧归赵</Data></Cell>
    <Cell><Data ss:Type="String">送给你，美丽，金碧辉煌</Data></Cell>
    <Cell ss:Index="13"><Data ss:Type="String">“完璧归赵”有个兄弟成语叫“价值连城”，故事中的和氏璧秦王愿以十五城池相换，这块无价珍宝至今下落依旧不明</Data></Cell>
    <Cell><Data ss:Type="String">百科</Data></Cell>
    <Cell><Data ss:Type="String">什么是和氏璧</Data></Cell>
    <Cell ss:StyleID="s18" ss:HRef="http://baike.baidu.com/link?url=90G2-nRaI-TJH5W6SaHwG7E6ClGbHbNg36FbKwRZzbzxsI8utEDbnuk09p7fGdTD"><Data
      ss:Type="String">http://baike.baidu.com/link?url=90G2-nRaI-TJH5W6SaHwG7E6ClGbHbNg36FbKwRZzbzxsI8utEDbnuk09p7fGdTD</Data></Cell>
   </Row>
   <Row ss:Height="48">
    <Cell><Data ss:Type="Number">7</Data></Cell>
    <Cell><Data ss:Type="String">画图</Data></Cell>
    <Cell ss:Index="4"><Data ss:Type="String">一只脚上插了香港区旗</Data></Cell>
    <Cell><Data ss:Type="String">冷知识</Data></Cell>
    <Cell><Data ss:Type="Number">2</Data></Cell>
    <Cell><Data ss:Type="String">猜一个词</Data></Cell>
    <Cell><Data ss:Type="String">痒啊痒啊~喵</Data></Cell>
    <Cell><Data ss:Type="String">香港脚</Data></Cell>
    <Cell><Data ss:Type="String">台湾，英国，头发，耳朵</Data></Cell>
    <Cell ss:Index="13"><Data ss:Type="String">香港同胞真冤啊，英国大兵得脚气，台湾翻译不动脑，从此脚气就挂上了香港脚的美名</Data></Cell>
    <Cell><Data ss:Type="String">百科</Data></Cell>
    <Cell><Data ss:Type="String">香港脚的由来</Data></Cell>
    <Cell ss:StyleID="s18" ss:HRef="http://zhidao.baidu.com/question/102486665.html"><Data
      ss:Type="String">http://zhidao.baidu.com/question/102486665.html </Data></Cell>
   </Row>
   <Row ss:Height="36">
    <Cell><Data ss:Type="Number">8</Data></Cell>
    <Cell><Data ss:Type="String">画图</Data></Cell>
    <Cell ss:Index="4"><Data ss:Type="String">杨幂肖像</Data></Cell>
    <Cell><Data ss:Type="String">明星</Data></Cell>
    <Cell><Data ss:Type="Number">2</Data></Cell>
    <Cell><Data ss:Type="String">这是哪个女演员</Data></Cell>
    <Cell><Data ss:Type="String">她的生意很有特色哦</Data></Cell>
    <Cell><Data ss:Type="String">杨幂</Data></Cell>
    <Cell><Data ss:Type="String">陶晶莹，林志玲，徐小凤</Data></Cell>
    <Cell ss:Index="13"><Data ss:Type="String">你知道为什么网民都说杨MM脚臭么？看看下面的视频就知道了</Data></Cell>
    <Cell><Data ss:Type="String">视频</Data></Cell>
    <Cell><Data ss:Type="String">给力星期天 72分钟见答案</Data></Cell>
    <Cell ss:StyleID="s18" ss:HRef="http://v.sohu.com/20110214/n279326831.shtml#hf"><Data
      ss:Type="String">http://v.sohu.com/20110214/n279326831.shtml#hf</Data></Cell>
   </Row>
   <Row ss:Height="24">
    <Cell><Data ss:Type="Number">9</Data></Cell>
    <Cell><Data ss:Type="String">画图</Data></Cell>
    <Cell ss:Index="4"><Data ss:Type="String">蒙娜丽莎的微笑</Data></Cell>
    <Cell><Data ss:Type="String">画作</Data></Cell>
    <Cell><Data ss:Type="Number">2</Data></Cell>
    <Cell><Data ss:Type="String">猜一副名画</Data></Cell>
    <Cell><Data ss:Type="String">你的笑容最美丽</Data></Cell>
    <Cell><Data ss:Type="String">蒙娜丽莎的微笑</Data></Cell>
    <Cell><Data ss:Type="String">喜悦，爱因斯坦，达芬奇</Data></Cell>
    <Cell ss:Index="13"><Data ss:Type="String">蒙娜丽莎之谜，她的笑容为何时隐时现？</Data></Cell>
    <Cell><Data ss:Type="String">视频</Data></Cell>
    <Cell><Data ss:Type="String">蒙娜丽莎的微笑之谜</Data></Cell>
    <Cell ss:StyleID="s18" ss:HRef="http://www.letv.com/ptv/vplay/609533.html"><Data
      ss:Type="String">http://www.letv.com/ptv/vplay/609533.html</Data></Cell>
   </Row>
   <Row ss:Height="84">
    <Cell><Data ss:Type="Number">10</Data></Cell>
    <Cell><Data ss:Type="String">画图</Data></Cell>
    <Cell ss:Index="4"><Data ss:Type="String">向日葵</Data></Cell>
    <Cell><Data ss:Type="String">画作</Data></Cell>
    <Cell><Data ss:Type="Number">3</Data></Cell>
    <Cell><Data ss:Type="String">猜一副名画</Data></Cell>
    <Cell><Data ss:Type="String">向日葵</Data></Cell>
    <Cell><Data ss:Type="String">梵高的作品</Data></Cell>
    <Cell><Data ss:Type="String">葵花籽，太，光，黄色</Data></Cell>
    <Cell ss:Index="13"><Data ss:Type="String">号称疯狂画家的梵高做了很多疯狂的事情，他咆哮着、怒吼着，吃着颜料，喝着松节油，还切下了一大块自己的耳朵，直至37岁，他用手枪终结了自己的生命。</Data></Cell>
    <Cell><Data ss:Type="String">百科</Data></Cell>
    <Cell><Data ss:Type="String">梵高的百科</Data></Cell>
    <Cell ss:StyleID="s18" ss:HRef="http://baike.baidu.com/link?url=8zS5AC0AFl-dnFcOFN-P66PLszDeZzCyK8E05DAHxUK1hIl5LsnP9-DPHwY9dtr3QWOivzAR9j3gGDGwk4DTn_"><Data
      ss:Type="String">http://baike.baidu.com/link?url=8zS5AC0AFl-dnFcOFN-P66PLszDeZzCyK8E05DAHxUK1hIl5LsnP9-DPHwY9dtr3QWOivzAR9j3gGDGwk4DTn_</Data></Cell>
   </Row>
   <Row ss:Height="60">
    <Cell><Data ss:Type="Number">11</Data></Cell>
    <Cell><Data ss:Type="String">偷听</Data></Cell>
    <Cell ss:Index="4"><Data ss:Type="String">黑猫警长</Data></Cell>
    <Cell><Data ss:Type="String">经典动画</Data></Cell>
    <Cell><Data ss:Type="Number">3</Data></Cell>
    <Cell><Data ss:Type="String">这是哪部经典动画的主题曲</Data></Cell>
    <Cell><Data ss:Type="String">黑猫警长</Data></Cell>
    <Cell><Data ss:Type="String">唱~眼睛瞪的像铜铃</Data></Cell>
    <Cell><Data ss:Type="String">白，手枪，老鼠，特务</Data></Cell>
    <Cell ss:Index="13"><Data ss:Type="String">什么？黑猫警长只有5集。据说由于内容太暴力血腥，经典作品黑猫警长只播出了5集，更有传闻黑猫警长的设定与纳粹有关系</Data></Cell>
    <Cell><Data ss:Type="String">视频</Data></Cell>
    <Cell><Data ss:Type="String">黑猫警长全5集</Data></Cell>
    <Cell ss:StyleID="s18" ss:HRef="http://v.qq.com/cover/a/akaae6jw3qprvc6.html"><Data
      ss:Type="String">http://v.qq.com/cover/a/akaae6jw3qprvc6.html</Data></Cell>
   </Row>
   <Row>
    <Cell><Data ss:Type="Number">12</Data></Cell>
    <Cell ss:Index="4"><Data ss:Type="String">葫芦娃</Data></Cell>
    <Cell><Data ss:Type="String">经典动画</Data></Cell>
    <Cell><Data ss:Type="Number">1</Data></Cell>
    <Cell ss:Index="9"><Data ss:Type="String">葫芦娃</Data></Cell>
   </Row>
   <Row>
    <Cell><Data ss:Type="Number">13</Data></Cell>
    <Cell ss:Index="4"><Data ss:Type="String">聪明的一休</Data></Cell>
    <Cell><Data ss:Type="String">经典动画</Data></Cell>
    <Cell><Data ss:Type="Number">1</Data></Cell>
    <Cell ss:Index="9"><Data ss:Type="String">聪明的一休</Data></Cell>
   </Row>
   <Row>
    <Cell><Data ss:Type="Number">14</Data></Cell>
    <Cell ss:Index="4"><Data ss:Type="String">花仙子</Data></Cell>
    <Cell><Data ss:Type="String">经典动画</Data></Cell>
    <Cell><Data ss:Type="Number">2</Data></Cell>
    <Cell ss:Index="9"><Data ss:Type="String">花仙子</Data></Cell>
   </Row>
   <Row>
    <Cell><Data ss:Type="Number">15</Data></Cell>
    <Cell ss:Index="4"><Data ss:Type="String">蓝精灵</Data></Cell>
    <Cell><Data ss:Type="String">经典动画</Data></Cell>
    <Cell><Data ss:Type="Number">1</Data></Cell>
    <Cell ss:Index="9"><Data ss:Type="String">蓝精灵</Data></Cell>
   </Row>
   <Row>
    <Cell><Data ss:Type="Number">16</Data></Cell>
    <Cell ss:Index="4"><Data ss:Type="String">机器猫</Data></Cell>
    <Cell><Data ss:Type="String">经典动画</Data></Cell>
    <Cell><Data ss:Type="Number">1</Data></Cell>
    <Cell ss:Index="9"><Data ss:Type="String">机器猫</Data></Cell>
   </Row>
   <Row>
    <Cell><Data ss:Type="Number">17</Data></Cell>
    <Cell ss:Index="4"><Data ss:Type="String">猫和老鼠</Data></Cell>
    <Cell><Data ss:Type="String">经典动画</Data></Cell>
    <Cell><Data ss:Type="Number">1</Data></Cell>
    <Cell ss:Index="9"><Data ss:Type="String">猫和老鼠</Data></Cell>
   </Row>
   <Row>
    <Cell><Data ss:Type="Number">18</Data></Cell>
    <Cell ss:Index="4"><Data ss:Type="String">蜡笔小新</Data></Cell>
    <Cell><Data ss:Type="String">经典动画</Data></Cell>
    <Cell><Data ss:Type="Number">2</Data></Cell>
    <Cell ss:Index="9"><Data ss:Type="String">蜡笔小新</Data></Cell>
   </Row>
   <Row ss:Height="14">
    <Cell><Data ss:Type="Number">19</Data></Cell>
    <Cell ss:Index="4" ss:StyleID="s20"><Data ss:Type="String">舒克和贝塔</Data></Cell>
    <Cell><Data ss:Type="String">经典动画</Data></Cell>
    <Cell><Data ss:Type="Number">3</Data></Cell>
    <Cell ss:Index="9" ss:StyleID="s20"><Data ss:Type="String">舒克和贝塔</Data></Cell>
   </Row>
   <Row>
    <Cell><Data ss:Type="Number">20</Data></Cell>
    <Cell ss:Index="4"><Data ss:Type="String">阿凡提的故事</Data></Cell>
    <Cell><Data ss:Type="String">经典动画</Data></Cell>
    <Cell><Data ss:Type="Number">3</Data></Cell>
    <Cell ss:Index="9"><Data ss:Type="String">阿凡提的故事</Data></Cell>
   </Row>
   <Row>
    <Cell><Data ss:Type="Number">21</Data></Cell>
    <Cell ss:Index="4"><Data ss:Type="String">圣斗士星矢</Data></Cell>
    <Cell><Data ss:Type="String">经典动画</Data></Cell>
    <Cell><Data ss:Type="Number">2</Data></Cell>
    <Cell ss:Index="9"><Data ss:Type="String">圣斗士星矢</Data></Cell>
   </Row>
   <Row>
    <Cell><Data ss:Type="Number">22</Data></Cell>
    <Cell ss:Index="4"><Data ss:Type="String">大力水手</Data></Cell>
    <Cell><Data ss:Type="String">经典动画</Data></Cell>
    <Cell><Data ss:Type="Number">3</Data></Cell>
    <Cell ss:Index="9"><Data ss:Type="String">大力水手</Data></Cell>
   </Row>
   <Row>
    <Cell><Data ss:Type="Number">23</Data></Cell>
    <Cell ss:Index="4" ss:StyleID="s19"><Data ss:Type="String">足球小将</Data></Cell>
    <Cell><Data ss:Type="String">经典动画</Data></Cell>
    <Cell><Data ss:Type="Number">3</Data></Cell>
    <Cell ss:Index="9" ss:StyleID="s19"><Data ss:Type="String">足球小将</Data></Cell>
   </Row>
   <Row>
    <Cell><Data ss:Type="Number">24</Data></Cell>
    <Cell ss:Index="4"><Data ss:Type="String">天空战记</Data></Cell>
    <Cell><Data ss:Type="String">经典动画</Data></Cell>
    <Cell><Data ss:Type="Number">3</Data></Cell>
    <Cell ss:Index="9"><Data ss:Type="String">天空战记</Data></Cell>
   </Row>
   <Row>
    <Cell><Data ss:Type="Number">25</Data></Cell>
    <Cell ss:Index="4"><Data ss:Type="String">灌篮高手</Data></Cell>
    <Cell><Data ss:Type="String">经典动画</Data></Cell>
    <Cell><Data ss:Type="Number">3</Data></Cell>
    <Cell ss:Index="9"><Data ss:Type="String">灌篮高手</Data></Cell>
   </Row>
   <Row>
    <Cell><Data ss:Type="Number">26</Data></Cell>
    <Cell ss:Index="4"><Data ss:Type="String">巴巴爸爸</Data></Cell>
    <Cell><Data ss:Type="String">经典动画</Data></Cell>
    <Cell><Data ss:Type="Number">3</Data></Cell>
    <Cell ss:Index="9"><Data ss:Type="String">巴巴爸爸</Data></Cell>
   </Row>
   <Row>
    <Cell><Data ss:Type="Number">27</Data></Cell>
    <Cell ss:Index="4"><Data ss:Type="String">恐龙特急克塞号</Data></Cell>
    <Cell><Data ss:Type="String">经典动画</Data></Cell>
    <Cell><Data ss:Type="Number">3</Data></Cell>
    <Cell ss:Index="9"><Data ss:Type="String">恐龙特急克塞号</Data></Cell>
   </Row>
   <Row>
    <Cell><Data ss:Type="Number">28</Data></Cell>
    <Cell ss:Index="4"><Data ss:Type="String">七龙珠</Data></Cell>
    <Cell><Data ss:Type="String">经典动画</Data></Cell>
    <Cell><Data ss:Type="Number">2</Data></Cell>
    <Cell ss:Index="9"><Data ss:Type="String">七龙珠</Data></Cell>
   </Row>
   <Row>
    <Cell><Data ss:Type="Number">29</Data></Cell>
    <Cell ss:Index="4"><Data ss:Type="String">我要代表月亮…</Data></Cell>
    <Cell><Data ss:Type="String">经典动画</Data></Cell>
    <Cell><Data ss:Type="Number">2</Data></Cell>
    <Cell ss:Index="9"><Data ss:Type="String">美少女战士</Data></Cell>
   </Row>
   <Row>
    <Cell ss:Index="4"><Data ss:Type="String">樱桃小丸子</Data></Cell>
    <Cell><Data ss:Type="String">经典动画</Data></Cell>
    <Cell><Data ss:Type="Number">2</Data></Cell>
    <Cell ss:Index="9"><Data ss:Type="String">樱桃小丸子</Data></Cell>
   </Row>
   <Row ss:Index="33">
    <Cell><Data ss:Type="Number">30</Data></Cell>
    <Cell ss:Index="4"><Data ss:Type="String">西游记</Data></Cell>
    <Cell><Data ss:Type="String">经典老剧</Data></Cell>
    <Cell ss:Index="9"><Data ss:Type="String">西游记</Data></Cell>
   </Row>
   <Row>
    <Cell><Data ss:Type="Number">31</Data></Cell>
    <Cell ss:Index="4"><Data ss:Type="String">还珠格格</Data></Cell>
    <Cell><Data ss:Type="String">经典老剧</Data></Cell>
    <Cell ss:Index="9"><Data ss:Type="String">还珠格格</Data></Cell>
    <Cell ss:Index="13"><Data ss:Type="String">王近山</Data></Cell>
   </Row>
   <Row>
    <Cell><Data ss:Type="Number">32</Data></Cell>
    <Cell ss:Index="4"><Data ss:Type="String">亮剑</Data></Cell>
    <Cell><Data ss:Type="String">经典老剧</Data></Cell>
    <Cell ss:Index="9"><Data ss:Type="String">亮剑</Data></Cell>
   </Row>
   <Row>
    <Cell><Data ss:Type="Number">33</Data></Cell>
    <Cell ss:Index="4"><Data ss:Type="String">新白娘子传奇</Data></Cell>
    <Cell><Data ss:Type="String">经典老剧</Data></Cell>
    <Cell ss:Index="9"><Data ss:Type="String">新白娘子传奇</Data></Cell>
   </Row>
   <Row>
    <Cell><Data ss:Type="Number">34</Data></Cell>
    <Cell ss:Index="4"><Data ss:Type="String">射雕英雄传</Data></Cell>
    <Cell><Data ss:Type="String">经典老剧</Data></Cell>
    <Cell ss:Index="9"><Data ss:Type="String">射雕英雄传</Data></Cell>
   </Row>
   <Row>
    <Cell ss:Index="4"><Data ss:Type="String">天龙八部</Data></Cell>
    <Cell><Data ss:Type="String">经典老剧</Data></Cell>
    <Cell ss:Index="9"><Data ss:Type="String">天龙八部</Data></Cell>
   </Row>
   <Row>
    <Cell ss:Index="4"><Data ss:Type="String">包青天</Data></Cell>
    <Cell><Data ss:Type="String">经典老剧</Data></Cell>
    <Cell ss:Index="9"><Data ss:Type="String">包青天</Data></Cell>
   </Row>
   <Row>
    <Cell ss:Index="4"><Data ss:Type="String">水浒传</Data></Cell>
    <Cell><Data ss:Type="String">经典老剧</Data></Cell>
    <Cell ss:Index="9"><Data ss:Type="String">水浒传</Data></Cell>
    <Cell ss:Index="13"><Data ss:Type="String">股市跌</Data></Cell>
   </Row>
   <Row>
    <Cell ss:Index="4"><Data ss:Type="String">戏说乾隆</Data></Cell>
    <Cell><Data ss:Type="String">经典老剧</Data></Cell>
    <Cell ss:Index="9"><Data ss:Type="String">戏说乾隆</Data></Cell>
   </Row>
   <Row>
    <Cell ss:Index="5"><Data ss:Type="String">经典老剧</Data></Cell>
    <Cell ss:Index="9"><Data ss:Type="String">铁齿铜牙纪晓岚</Data></Cell>
   </Row>
   <Row>
    <Cell ss:Index="5"><Data ss:Type="String">经典老剧</Data></Cell>
    <Cell ss:Index="9"><Data ss:Type="String">寻秦记</Data></Cell>
   </Row>
   <Row ss:Index="45" ss:Height="24">
    <Cell ss:Index="4"><Data ss:Type="String">奋斗的经典台词</Data></Cell>
    <Cell><Data ss:Type="String">热播电视剧</Data></Cell>
    <Cell ss:Index="9"><Data ss:Type="String">奋斗</Data></Cell>
   </Row>
   <Row ss:Height="24">
    <Cell ss:Index="4"><Data ss:Type="String">甄嬛体台词</Data></Cell>
    <Cell><Data ss:Type="String">热播电视剧</Data></Cell>
    <Cell ss:Index="9"><Data ss:Type="String">甄嬛传</Data></Cell>
   </Row>
   <Row ss:Height="24">
    <Cell ss:Index="5"><Data ss:Type="String">热播电视剧</Data></Cell>
    <Cell ss:Index="9"><Data ss:Type="String">步步惊心</Data></Cell>
   </Row>
   <Row ss:Height="24">
    <Cell ss:Index="5"><Data ss:Type="String">热播电视剧</Data></Cell>
    <Cell ss:Index="9"><Data ss:Type="String">回家的诱惑</Data></Cell>
   </Row>
   <Row ss:Height="24">
    <Cell ss:Index="5"><Data ss:Type="String">热播电视剧</Data></Cell>
    <Cell ss:Index="9"><Data ss:Type="String">北京爱情故事</Data></Cell>
   </Row>
   <Row ss:Height="24">
    <Cell ss:Index="5"><Data ss:Type="String">热播电视剧</Data></Cell>
    <Cell ss:Index="9"><Data ss:Type="String">金枝欲孽</Data></Cell>
   </Row>
   <Row ss:Height="24">
    <Cell ss:Index="5"><Data ss:Type="String">热播电视剧</Data></Cell>
    <Cell ss:Index="9"><Data ss:Type="String">蜗居</Data></Cell>
   </Row>
   <Row ss:Height="24">
    <Cell ss:Index="5"><Data ss:Type="String">热播电视剧</Data></Cell>
    <Cell ss:Index="9"><Data ss:Type="String">我和僵尸有个约会</Data></Cell>
   </Row>
   <Row ss:Height="24">
    <Cell ss:Index="5"><Data ss:Type="String">热播电视剧</Data></Cell>
    <Cell ss:Index="9"><Data ss:Type="String">仙剑奇侠传</Data></Cell>
   </Row>
   <Row ss:Height="24">
    <Cell ss:Index="5"><Data ss:Type="String">热播电视剧</Data></Cell>
    <Cell ss:Index="9"><Data ss:Type="String">倾世皇妃</Data></Cell>
   </Row>
   <Row ss:Height="24">
    <Cell ss:Index="5"><Data ss:Type="String">热播电视剧</Data></Cell>
   </Row>
   <Row ss:Index="65">
    <Cell ss:Index="5"><Data ss:Type="String">经典节目</Data></Cell>
    <Cell ss:Index="9"><Data ss:Type="String">新闻联播</Data></Cell>
   </Row>
   <Row>
    <Cell ss:Index="5"><Data ss:Type="String">经典节目</Data></Cell>
    <Cell ss:Index="9"><Data ss:Type="String">动物世界</Data></Cell>
   </Row>
   <Row>
    <Cell ss:Index="5"><Data ss:Type="String">经典节目</Data></Cell>
    <Cell ss:Index="9"><Data ss:Type="String">康熙来了</Data></Cell>
   </Row>
   <Row>
    <Cell ss:Index="5"><Data ss:Type="String">经典节目</Data></Cell>
    <Cell ss:Index="9"><Data ss:Type="String">非诚勿扰</Data></Cell>
   </Row>
   <Row>
    <Cell ss:Index="5"><Data ss:Type="String">经典节目</Data></Cell>
    <Cell ss:Index="9"><Data ss:Type="String">中国好声音</Data></Cell>
   </Row>
   <Row>
    <Cell ss:Index="5"><Data ss:Type="String">经典节目</Data></Cell>
    <Cell ss:Index="9"><Data ss:Type="String">天天向上</Data></Cell>
   </Row>
   <Row>
    <Cell ss:Index="5"><Data ss:Type="String">经典节目</Data></Cell>
    <Cell ss:Index="9"><Data ss:Type="String">快乐大本营</Data></Cell>
   </Row>
   <Row>
    <Cell ss:Index="5"><Data ss:Type="String">经典节目</Data></Cell>
    <Cell ss:Index="9"><Data ss:Type="String">锵锵三人行</Data></Cell>
   </Row>
   <Row>
    <Cell ss:Index="5"><Data ss:Type="String">经典节目</Data></Cell>
    <Cell ss:Index="9"><Data ss:Type="String">一站到底</Data></Cell>
   </Row>
   <Row ss:Index="76">
    <Cell ss:Index="5"><Data ss:Type="String">热播动画</Data></Cell>
    <Cell ss:Index="9"><Data ss:Type="String">蓝猫</Data></Cell>
   </Row>
   <Row>
    <Cell ss:Index="5"><Data ss:Type="String">热播动画</Data></Cell>
    <Cell ss:Index="9"><Data ss:Type="String">喜羊羊和灰太狼</Data></Cell>
   </Row>
   <Row>
    <Cell ss:Index="5"><Data ss:Type="String">热播动画</Data></Cell>
    <Cell ss:Index="9"><Data ss:Type="String">火影忍者</Data></Cell>
   </Row>
   <Row>
    <Cell ss:Index="5"><Data ss:Type="String">热播动画</Data></Cell>
    <Cell ss:Index="9"><Data ss:Type="String">海贼王</Data></Cell>
   </Row>
   <Row>
    <Cell ss:Index="5"><Data ss:Type="String">热播动画</Data></Cell>
    <Cell ss:Index="9"><Data ss:Type="String">十万个冷笑话</Data></Cell>
   </Row>
   <Row>
    <Cell ss:Index="5"><Data ss:Type="String">热播动画</Data></Cell>
    <Cell ss:Index="9"><Data ss:Type="String">进击的巨人</Data></Cell>
   </Row>
   <Row>
    <Cell ss:Index="5"><Data ss:Type="String">热播动画</Data></Cell>
    <Cell ss:Index="9"><Data ss:Type="String">天线宝宝</Data></Cell>
   </Row>
   <Row>
    <Cell ss:Index="5"><Data ss:Type="String">热播动画</Data></Cell>
   </Row>
   <Row>
    <Cell ss:Index="5"><Data ss:Type="String">热播动画</Data></Cell>
   </Row>
   <Row>
    <Cell ss:Index="5"><Data ss:Type="String">热播动画</Data></Cell>
   </Row>
   <Row ss:Index="88">
    <Cell ss:Index="5"><Data ss:Type="String">经典韩剧</Data></Cell>
    <Cell ss:Index="9"><Data ss:Type="String">蓝色生死恋</Data></Cell>
   </Row>
   <Row>
    <Cell ss:Index="5"><Data ss:Type="String">经典韩剧</Data></Cell>
    <Cell ss:Index="9"><Data ss:Type="String">大长今</Data></Cell>
   </Row>
   <Row>
    <Cell ss:Index="5"><Data ss:Type="String">经典韩剧</Data></Cell>
    <Cell ss:Index="9"><Data ss:Type="String">哈佛爱情故事</Data></Cell>
   </Row>
   <Row>
    <Cell ss:Index="5"><Data ss:Type="String">经典韩剧</Data></Cell>
    <Cell ss:Index="9"><Data ss:Type="String">对不起我爱你</Data></Cell>
   </Row>
   <Row>
    <Cell ss:Index="5"><Data ss:Type="String">经典韩剧</Data></Cell>
    <Cell ss:Index="9"><Data ss:Type="String">豪杰春香</Data></Cell>
   </Row>
   <Row>
    <Cell ss:Index="5"><Data ss:Type="String">经典韩剧</Data></Cell>
    <Cell ss:Index="9"><Data ss:Type="String">我的名字叫金三顺</Data></Cell>
   </Row>
   <Row>
    <Cell ss:Index="5"><Data ss:Type="String">经典韩剧</Data></Cell>
    <Cell ss:Index="9"><Data ss:Type="String">天国的阶梯</Data></Cell>
   </Row>
   <Row>
    <Cell ss:Index="5"><Data ss:Type="String">经典韩剧</Data></Cell>
    <Cell ss:Index="9"><Data ss:Type="String">浪漫满屋</Data></Cell>
   </Row>
   <Row>
    <Cell ss:Index="5"><Data ss:Type="String">经典韩剧</Data></Cell>
    <Cell ss:Index="9"><Data ss:Type="String">人鱼小姐</Data></Cell>
   </Row>
   <Row ss:Index="98">
    <Cell ss:Index="5"><Data ss:Type="String">经典广告</Data></Cell>
   </Row>
   <Row>
    <Cell ss:Index="5"><Data ss:Type="String">经典广告</Data></Cell>
   </Row>
   <Row>
    <Cell ss:Index="5"><Data ss:Type="String">经典广告</Data></Cell>
   </Row>
   <Row>
    <Cell ss:Index="5"><Data ss:Type="String">经典广告</Data></Cell>
   </Row>
   <Row>
    <Cell ss:Index="5"><Data ss:Type="String">经典广告</Data></Cell>
   </Row>
   <Row>
    <Cell ss:Index="5"><Data ss:Type="String">经典广告</Data></Cell>
   </Row>
   <Row>
    <Cell ss:Index="5"><Data ss:Type="String">经典广告</Data></Cell>
   </Row>
   <Row>
    <Cell ss:Index="5"><Data ss:Type="String">经典广告</Data></Cell>
   </Row>
   <Row>
    <Cell ss:Index="5"><Data ss:Type="String">经典广告</Data></Cell>
   </Row>
   <Row>
    <Cell ss:Index="5"><Data ss:Type="String">经典广告</Data></Cell>
   </Row>
   <Row>
    <Cell ss:Index="5"><Data ss:Type="String">经典广告</Data></Cell>
   </Row>
   <Row ss:Index="110">
    <Cell ss:Index="5"><Data ss:Type="String">经典游戏</Data></Cell>
    <Cell ss:Index="9"><Data ss:Type="String">仙剑奇侠传</Data></Cell>
   </Row>
   <Row>
    <Cell ss:Index="5"><Data ss:Type="String">经典游戏</Data></Cell>
    <Cell ss:Index="9"><Data ss:Type="String">天天连盟</Data></Cell>
   </Row>
   <Row>
    <Cell ss:Index="5"><Data ss:Type="String">经典游戏</Data></Cell>
    <Cell ss:Index="9"><Data ss:Type="String">英雄联盟</Data></Cell>
   </Row>
   <Row>
    <Cell ss:Index="5"><Data ss:Type="String">经典游戏</Data></Cell>
    <Cell ss:Index="9"><Data ss:Type="String">魔兽世界</Data></Cell>
   </Row>
   <Row>
    <Cell ss:Index="5"><Data ss:Type="String">经典游戏</Data></Cell>
    <Cell ss:Index="9"><Data ss:Type="String">植物大战僵尸</Data></Cell>
   </Row>
   <Row>
    <Cell ss:Index="5"><Data ss:Type="String">经典游戏</Data></Cell>
    <Cell ss:Index="9"><Data ss:Type="String">保卫萝卜</Data></Cell>
   </Row>
   <Row>
    <Cell ss:Index="5"><Data ss:Type="String">经典游戏</Data></Cell>
    <Cell ss:Index="9"><Data ss:Type="String">愤怒的小鸟</Data></Cell>
   </Row>
   <Row>
    <Cell ss:Index="5"><Data ss:Type="String">经典游戏</Data></Cell>
    <Cell ss:Index="9"><Data ss:Type="String">太鼓达人</Data></Cell>
   </Row>
   <Row>
    <Cell ss:Index="5"><Data ss:Type="String">经典游戏</Data></Cell>
    <Cell ss:Index="9"><Data ss:Type="String">超级玛丽</Data></Cell>
   </Row>
   <Row>
    <Cell ss:Index="5"><Data ss:Type="String">经典游戏</Data></Cell>
    <Cell ss:Index="9"><Data ss:Type="String">魂斗罗</Data></Cell>
   </Row>
   <Row>
    <Cell ss:Index="5"><Data ss:Type="String">经典游戏</Data></Cell>
    <Cell ss:Index="9"><Data ss:Type="String">松鼠大战</Data></Cell>
   </Row>
   <Row ss:Index="122">
    <Cell ss:Index="5"><Data ss:Type="String">猜外语</Data></Cell>
    <Cell ss:Index="9"><Data ss:Type="String">日语</Data></Cell>
   </Row>
   <Row>
    <Cell ss:Index="5"><Data ss:Type="String">猜外语</Data></Cell>
    <Cell ss:Index="9"><Data ss:Type="String">韩语</Data></Cell>
   </Row>
   <Row>
    <Cell ss:Index="5"><Data ss:Type="String">猜外语</Data></Cell>
    <Cell ss:Index="9"><Data ss:Type="String">英语</Data></Cell>
   </Row>
   <Row>
    <Cell ss:Index="5"><Data ss:Type="String">猜外语</Data></Cell>
    <Cell ss:Index="9"><Data ss:Type="String">法语</Data></Cell>
   </Row>
   <Row>
    <Cell ss:Index="5"><Data ss:Type="String">猜外语</Data></Cell>
    <Cell ss:Index="9"><Data ss:Type="String">德语</Data></Cell>
   </Row>
   <Row>
    <Cell ss:Index="5"><Data ss:Type="String">猜外语</Data></Cell>
    <Cell ss:Index="9"><Data ss:Type="String">俄语</Data></Cell>
   </Row>
   <Row ss:Index="129">
    <Cell ss:Index="5"><Data ss:Type="String">猜方言</Data></Cell>
    <Cell ss:Index="9"><Data ss:Type="String">四川人</Data></Cell>
   </Row>
   <Row>
    <Cell ss:Index="5"><Data ss:Type="String">猜方言</Data></Cell>
    <Cell ss:Index="9"><Data ss:Type="String">广东人</Data></Cell>
   </Row>
   <Row>
    <Cell ss:Index="5"><Data ss:Type="String">猜方言</Data></Cell>
    <Cell ss:Index="9"><Data ss:Type="String">北京人</Data></Cell>
   </Row>
   <Row>
    <Cell ss:Index="5"><Data ss:Type="String">猜方言</Data></Cell>
    <Cell ss:Index="9"><Data ss:Type="String">东北</Data></Cell>
   </Row>
   <Row>
    <Cell ss:Index="5"><Data ss:Type="String">猜方言</Data></Cell>
    <Cell ss:Index="9"><Data ss:Type="String">上海话</Data></Cell>
   </Row>
   <Row>
    <Cell ss:Index="5"><Data ss:Type="String">猜方言</Data></Cell>
    <Cell ss:Index="9"><Data ss:Type="String">天津</Data></Cell>
   </Row>
   <Row>
    <Cell ss:Index="5"><Data ss:Type="String">猜方言</Data></Cell>
    <Cell ss:Index="9"><Data ss:Type="String">河南</Data></Cell>
   </Row>
   <Row ss:Index="137">
    <Cell ss:Index="5"><Data ss:Type="String">猜手机</Data></Cell>
    <Cell ss:Index="9"><Data ss:Type="String">苹果</Data></Cell>
    <Cell ss:Index="13"><Data ss:Type="String">卖肾</Data></Cell>
   </Row>
   <Row>
    <Cell ss:Index="5"><Data ss:Type="String">猜手机</Data></Cell>
    <Cell ss:Index="9"><Data ss:Type="String">摩托罗拉</Data></Cell>
    <Cell ss:Index="13"><Data ss:Type="String">moto X</Data></Cell>
   </Row>
   <Row>
    <Cell ss:Index="5"><Data ss:Type="String">猜手机</Data></Cell>
    <Cell ss:Index="9"><Data ss:Type="String">诺基亚</Data></Cell>
    <Cell ss:Index="13"><Data ss:Type="String">1020介绍</Data></Cell>
   </Row>
   <Row>
    <Cell ss:Index="5"><Data ss:Type="String">猜手机</Data></Cell>
    <Cell ss:Index="9"><Data ss:Type="String">小米</Data></Cell>
    <Cell ss:Index="13"><Data ss:Type="String">100亿</Data></Cell>
   </Row>
   <Row>
    <Cell ss:Index="5"><Data ss:Type="String">猜手机</Data></Cell>
    <Cell ss:Index="9"><Data ss:Type="String">三星</Data></Cell>
   </Row>
   <Row ss:Index="144">
    <Cell ss:Index="5"><Data ss:Type="String">行为</Data></Cell>
    <Cell ss:Index="9"><Data ss:Type="String">睡觉</Data></Cell>
   </Row>
   <Row>
    <Cell ss:Index="5"><Data ss:Type="String">行为</Data></Cell>
    <Cell ss:Index="9"><Data ss:Type="String">做爱</Data></Cell>
   </Row>
   <Row>
    <Cell ss:Index="5"><Data ss:Type="String">行为</Data></Cell>
    <Cell ss:Index="9"><Data ss:Type="String">做饭</Data></Cell>
   </Row>
   <Row>
    <Cell ss:Index="5"><Data ss:Type="String">行为</Data></Cell>
   </Row>
   <Row>
    <Cell ss:Index="5"><Data ss:Type="String">行为</Data></Cell>
   </Row>
   <Row>
    <Cell ss:Index="5"><Data ss:Type="String">行为</Data></Cell>
   </Row>
   <Row>
    <Cell ss:Index="5"><Data ss:Type="String">行为</Data></Cell>
   </Row>
   <Row>
    <Cell ss:Index="5"><Data ss:Type="String">行为</Data></Cell>
   </Row>
   <Row>
    <Cell ss:Index="5"><Data ss:Type="String">行为</Data></Cell>
   </Row>
   <Row ss:Index="155">
    <Cell ss:Index="5"><Data ss:Type="String">动物</Data></Cell>
    <Cell ss:Index="9"><Data ss:Type="String">马</Data></Cell>
   </Row>
   <Row>
    <Cell ss:Index="5"><Data ss:Type="String">动物</Data></Cell>
    <Cell ss:Index="9"><Data ss:Type="String">猫</Data></Cell>
   </Row>
   <Row>
    <Cell ss:Index="5"><Data ss:Type="String">动物</Data></Cell>
    <Cell ss:Index="9"><Data ss:Type="String">狗</Data></Cell>
   </Row>
   <Row>
    <Cell ss:Index="5"><Data ss:Type="String">动物</Data></Cell>
    <Cell ss:Index="9"><Data ss:Type="String">乌鸦</Data></Cell>
   </Row>
   <Row>
    <Cell ss:Index="5"><Data ss:Type="String">动物</Data></Cell>
    <Cell ss:Index="9"><Data ss:Type="String">牛</Data></Cell>
   </Row>
   <Row>
    <Cell ss:Index="5"><Data ss:Type="String">动物</Data></Cell>
    <Cell ss:Index="9"><Data ss:Type="String">羊</Data></Cell>
   </Row>
   <Row>
    <Cell ss:Index="5"><Data ss:Type="String">动物</Data></Cell>
    <Cell ss:Index="9"><Data ss:Type="String">猪</Data></Cell>
   </Row>
   <Row>
    <Cell ss:Index="5"><Data ss:Type="String">动物</Data></Cell>
    <Cell ss:Index="9"><Data ss:Type="String">鹦鹉</Data></Cell>
   </Row>
   <Row ss:Index="164">
    <Cell ss:Index="5"><Data ss:Type="String">乐器</Data></Cell>
    <Cell ss:Index="9"><Data ss:Type="String">钢琴</Data></Cell>
   </Row>
   <Row>
    <Cell ss:Index="5"><Data ss:Type="String">乐器</Data></Cell>
    <Cell ss:Index="9"><Data ss:Type="String">小提琴</Data></Cell>
   </Row>
   <Row>
    <Cell ss:Index="5"><Data ss:Type="String">乐器</Data></Cell>
    <Cell ss:Index="9"><Data ss:Type="String">吉他</Data></Cell>
   </Row>
   <Row>
    <Cell ss:Index="5"><Data ss:Type="String">乐器</Data></Cell>
    <Cell ss:Index="9"><Data ss:Type="String">贝斯</Data></Cell>
   </Row>
   <Row>
    <Cell ss:Index="5"><Data ss:Type="String">乐器</Data></Cell>
    <Cell ss:Index="9"><Data ss:Type="String">大提琴</Data></Cell>
   </Row>
   <Row>
    <Cell ss:Index="5"><Data ss:Type="String">乐器</Data></Cell>
    <Cell ss:Index="9"><Data ss:Type="String">笛子</Data></Cell>
   </Row>
   <Row>
    <Cell ss:Index="5"><Data ss:Type="String">乐器</Data></Cell>
    <Cell ss:Index="9"><Data ss:Type="String">萨克斯</Data></Cell>
   </Row>
   <Row>
    <Cell ss:Index="5"><Data ss:Type="String">乐器</Data></Cell>
    <Cell ss:Index="9"><Data ss:Type="String">爵士鼓$架子鼓</Data></Cell>
   </Row>
   <Row>
    <Cell ss:Index="5"><Data ss:Type="String">乐器</Data></Cell>
    <Cell ss:Index="9"><Data ss:Type="String">口琴</Data></Cell>
   </Row>
   <Row>
    <Cell ss:Index="5"><Data ss:Type="String">乐器</Data></Cell>
    <Cell ss:Index="9"><Data ss:Type="String">古筝</Data></Cell>
   </Row>
   <Row>
    <Cell ss:Index="5"><Data ss:Type="String">乐器</Data></Cell>
    <Cell ss:Index="9"><Data ss:Type="String">风笛</Data></Cell>
   </Row>
   <Row>
    <Cell ss:Index="5"><Data ss:Type="String">乐器</Data></Cell>
    <Cell ss:Index="9"><Data ss:Type="String">唢呐</Data></Cell>
   </Row>
   <Row>
    <Cell ss:Index="5"><Data ss:Type="String">乐器</Data></Cell>
    <Cell ss:Index="9"><Data ss:Type="String">二胡</Data></Cell>
   </Row>
   <Row>
    <Cell ss:Index="5"><Data ss:Type="String">乐器</Data></Cell>
    <Cell ss:Index="9"><Data ss:Type="String">竖琴</Data></Cell>
   </Row>
   <Row ss:Index="180" ss:Height="48">
    <Cell><Data ss:Type="Number">2</Data></Cell>
    <Cell><Data ss:Type="String">偷听</Data></Cell>
    <Cell ss:Index="4"><Data ss:Type="String">最炫民族风</Data></Cell>
    <Cell><Data ss:Type="String">神曲</Data></Cell>
    <Cell><Data ss:Type="Number">1</Data></Cell>
    <Cell><Data ss:Type="String">这是哪首神曲啊？</Data></Cell>
    <Cell><Data ss:Type="String">那个什么凤凰组合…</Data></Cell>
    <Cell><Data ss:Type="String">最炫民族风</Data></Cell>
    <Cell><Data ss:Type="String">忐忑，国歌，吻别，爱你一万年</Data></Cell>
    <Cell><Data ss:Type="String">mp0001</Data></Cell>
    <Cell><Data ss:Type="String">惊吓的野猪</Data></Cell>
    <Cell><Data ss:Type="String">为了防止野猪来袭，辽阳县八会镇宽厂峪村的村民们放起了最炫民族风，随之野猪闻取逃，神曲果然是神曲。</Data></Cell>
    <Cell><Data ss:Type="String">音乐</Data></Cell>
    <Cell><Data ss:Type="String">最炫民族风试听</Data></Cell>
    <Cell ss:StyleID="s18" ss:HRef="http://music.baidu.com/#/!/song/246301?rate=%E6%99%AE%E9%80%9A%E7%89%88&amp;fm=ald"><Data
      ss:Type="String">http://music.baidu.com/#/!/song/246301?rate=%E6%99%AE%E9%80%9A%E7%89%88&amp;fm=ald</Data></Cell>
   </Row>
   <Row>
    <Cell ss:Index="5"><Data ss:Type="String">神曲</Data></Cell>
    <Cell ss:Index="9"><Data ss:Type="String">QQ爱</Data></Cell>
   </Row>
   <Row>
    <Cell ss:Index="5"><Data ss:Type="String">神曲</Data></Cell>
    <Cell ss:Index="9"><Data ss:Type="String">老鼠爱大米</Data></Cell>
   </Row>
   <Row>
    <Cell ss:Index="5"><Data ss:Type="String">神曲</Data></Cell>
    <Cell ss:Index="9"><Data ss:Type="String">伤不起</Data></Cell>
   </Row>
   <Row>
    <Cell ss:Index="5"><Data ss:Type="String">神曲</Data></Cell>
    <Cell ss:Index="9"><Data ss:Type="String">QQ爱</Data></Cell>
   </Row>
   <Row>
    <Cell ss:Index="5"><Data ss:Type="String">神曲</Data></Cell>
    <Cell ss:Index="9"><Data ss:Type="String">Nobody</Data></Cell>
   </Row>
   <Row>
    <Cell ss:Index="5"><Data ss:Type="String">神曲</Data></Cell>
    <Cell ss:Index="9"><Data ss:Type="String">忐忑</Data></Cell>
   </Row>
   <Row>
    <Cell ss:Index="5"><Data ss:Type="String">神曲</Data></Cell>
    <Cell ss:Index="9"><Data ss:Type="String">爱情买卖</Data></Cell>
   </Row>
   <Row>
    <Cell ss:Index="5"><Data ss:Type="String">神曲</Data></Cell>
    <Cell ss:Index="9"><Data ss:Type="String">狮子座</Data></Cell>
   </Row>
   <Row>
    <Cell ss:Index="5"><Data ss:Type="String">神曲</Data></Cell>
    <Cell ss:Index="9"><Data ss:Type="String">月亮之上</Data></Cell>
   </Row>
   <Row>
    <Cell ss:Index="5"><Data ss:Type="String">神曲</Data></Cell>
    <Cell ss:Index="9"><Data ss:Type="String">甩葱歌</Data></Cell>
   </Row>
   <Row>
    <Cell ss:Index="5"><Data ss:Type="String">神曲</Data></Cell>
    <Cell ss:Index="9"><Data ss:Type="String">因为爱情</Data></Cell>
   </Row>
   <Row ss:Index="194">
    <Cell ss:Index="5"><Data ss:Type="String">KTV</Data></Cell>
    <Cell ss:Index="9"><Data ss:Type="String">十年</Data></Cell>
   </Row>
   <Row>
    <Cell ss:Index="5"><Data ss:Type="String">KTV</Data></Cell>
    <Cell ss:Index="9"><Data ss:Type="String">后来</Data></Cell>
   </Row>
   <Row>
    <Cell ss:Index="5"><Data ss:Type="String">KTV</Data></Cell>
    <Cell ss:Index="9"><Data ss:Type="String">勇气</Data></Cell>
   </Row>
   <Row>
    <Cell ss:Index="5"><Data ss:Type="String">KTV</Data></Cell>
    <Cell ss:Index="9"><Data ss:Type="String">童话</Data></Cell>
   </Row>
   <Row>
    <Cell ss:Index="5"><Data ss:Type="String">KTV</Data></Cell>
    <Cell ss:Index="9"><Data ss:Type="String">死了都要爱</Data></Cell>
   </Row>
   <Row>
    <Cell ss:Index="5"><Data ss:Type="String">KTV</Data></Cell>
    <Cell ss:Index="9"><Data ss:Type="String">广岛之恋</Data></Cell>
   </Row>
   <Row>
    <Cell ss:Index="5"><Data ss:Type="String">KTV</Data></Cell>
    <Cell ss:Index="9"><Data ss:Type="String">红豆</Data></Cell>
   </Row>
   <Row>
    <Cell ss:Index="5"><Data ss:Type="String">KTV</Data></Cell>
    <Cell ss:Index="9"><Data ss:Type="String">可惜不是你</Data></Cell>
   </Row>
   <Row>
    <Cell ss:Index="5"><Data ss:Type="String">KTV</Data></Cell>
    <Cell ss:Index="9"><Data ss:Type="String">隐形的翅膀</Data></Cell>
   </Row>
   <Row>
    <Cell ss:Index="5"><Data ss:Type="String">KTV</Data></Cell>
    <Cell ss:Index="9"><Data ss:Type="String">倒带</Data></Cell>
   </Row>
   <Row>
    <Cell ss:Index="5"><Data ss:Type="String">KTV</Data></Cell>
    <Cell ss:Index="9"><Data ss:Type="String">离歌</Data></Cell>
   </Row>
   <Row>
    <Cell ss:Index="5"><Data ss:Type="String">KTV</Data></Cell>
    <Cell ss:Index="9"><Data ss:Type="String">甜蜜蜜</Data></Cell>
   </Row>
   <Row>
    <Cell ss:Index="5"><Data ss:Type="String">KTV</Data></Cell>
    <Cell ss:Index="9"><Data ss:Type="String">你把我灌醉</Data></Cell>
   </Row>
   <Row>
    <Cell ss:Index="5"><Data ss:Type="String">KTV</Data></Cell>
    <Cell ss:Index="9"><Data ss:Type="String">小情歌</Data></Cell>
   </Row>
   <Row>
    <Cell ss:Index="5"><Data ss:Type="String">KTV</Data></Cell>
    <Cell ss:Index="9"><Data ss:Type="String">大海</Data></Cell>
   </Row>
   <Row>
    <Cell ss:Index="5"><Data ss:Type="String">KTV</Data></Cell>
    <Cell ss:Index="9"><Data ss:Type="String">冰雨</Data></Cell>
   </Row>
   <Row>
    <Cell ss:Index="5"><Data ss:Type="String">KTV</Data></Cell>
    <Cell ss:Index="9"><Data ss:Type="String">听海</Data></Cell>
   </Row>
   <Row>
    <Cell ss:Index="5"><Data ss:Type="String">KTV</Data></Cell>
    <Cell ss:Index="9"><Data ss:Type="String">老男孩</Data></Cell>
   </Row>
   <Row>
    <Cell ss:Index="5"><Data ss:Type="String">KTV</Data></Cell>
    <Cell ss:Index="9"><Data ss:Type="String">K歌之王</Data></Cell>
   </Row>
   <Row>
    <Cell ss:Index="5"><Data ss:Type="String">KTV</Data></Cell>
    <Cell ss:Index="9"><Data ss:Type="String">千千阙歌</Data></Cell>
   </Row>
   <Row>
    <Cell ss:Index="5"><Data ss:Type="String">KTV</Data></Cell>
    <Cell ss:Index="9"><Data ss:Type="String">千里之外</Data></Cell>
   </Row>
   <Row>
    <Cell ss:Index="5"><Data ss:Type="String">KTV</Data></Cell>
    <Cell ss:Index="9"><Data ss:Type="String">爱如潮水</Data></Cell>
   </Row>
   <Row>
    <Cell ss:Index="5"><Data ss:Type="String">KTV</Data></Cell>
    <Cell ss:Index="9"><Data ss:Type="String">短发</Data></Cell>
   </Row>
   <Row>
    <Cell ss:Index="5"><Data ss:Type="String">KTV</Data></Cell>
    <Cell ss:Index="9"><Data ss:Type="String">单生情歌</Data></Cell>
   </Row>
   <Row>
    <Cell ss:Index="5"><Data ss:Type="String">KTV</Data></Cell>
    <Cell ss:Index="9"><Data ss:Type="String">至少还有你</Data></Cell>
   </Row>
   <Row>
    <Cell ss:Index="5"><Data ss:Type="String">KTV</Data></Cell>
    <Cell ss:Index="9"><Data ss:Type="String">唯一</Data></Cell>
   </Row>
   <Row>
    <Cell ss:Index="5"><Data ss:Type="String">KTV</Data></Cell>
    <Cell ss:Index="9"><Data ss:Type="String">痴心绝对</Data></Cell>
   </Row>
   <Row>
    <Cell ss:Index="5"><Data ss:Type="String">KTV</Data></Cell>
    <Cell ss:Index="9"><Data ss:Type="String">让我一次爱个够</Data></Cell>
   </Row>
   <Row>
    <Cell ss:Index="5"><Data ss:Type="String">KTV</Data></Cell>
    <Cell ss:Index="9"><Data ss:Type="String">独角戏</Data></Cell>
   </Row>
   <Row ss:Index="225">
    <Cell ss:Index="5"><Data ss:Type="String">猜表哥</Data></Cell>
   </Row>
   <Row>
    <Cell ss:Index="5"><Data ss:Type="String">猜表哥</Data></Cell>
    <Cell ss:Index="9"><Data ss:Type="String">百达翡丽</Data></Cell>
   </Row>
   <Row>
    <Cell ss:Index="5"><Data ss:Type="String">猜表哥</Data></Cell>
    <Cell ss:Index="9"><Data ss:Type="String">爱彼</Data></Cell>
   </Row>
   <Row>
    <Cell ss:Index="5"><Data ss:Type="String">猜表哥</Data></Cell>
    <Cell ss:Index="9"><Data ss:Type="String">朗格</Data></Cell>
   </Row>
   <Row>
    <Cell ss:Index="5"><Data ss:Type="String">猜表哥</Data></Cell>
    <Cell ss:Index="9"><Data ss:Type="String">江诗丹顿</Data></Cell>
   </Row>
   <Row>
    <Cell ss:Index="5"><Data ss:Type="String">猜表哥</Data></Cell>
    <Cell ss:Index="9"><Data ss:Type="String">宝丽爵</Data></Cell>
   </Row>
   <Row>
    <Cell ss:Index="5"><Data ss:Type="String">猜表哥</Data></Cell>
    <Cell ss:Index="9"><Data ss:Type="String">宝珀</Data></Cell>
   </Row>
   <Row>
    <Cell ss:Index="5"><Data ss:Type="String">猜表哥</Data></Cell>
    <Cell ss:Index="9"><Data ss:Type="String">积家</Data></Cell>
   </Row>
   <Row>
    <Cell ss:Index="5"><Data ss:Type="String">猜表哥</Data></Cell>
    <Cell ss:Index="9"><Data ss:Type="String">宝玑</Data></Cell>
   </Row>
   <Row>
    <Cell ss:Index="5"><Data ss:Type="String">猜表哥</Data></Cell>
    <Cell ss:Index="9"><Data ss:Type="String">卡地亚</Data></Cell>
   </Row>
   <Row>
    <Cell ss:Index="5"><Data ss:Type="String">猜表哥</Data></Cell>
    <Cell ss:Index="9"><Data ss:Type="String">劳力士</Data></Cell>
   </Row>
   <Row>
    <Cell ss:Index="5"><Data ss:Type="String">猜表哥</Data></Cell>
    <Cell ss:Index="9"><Data ss:Type="String">万国</Data></Cell>
   </Row>
   <Row>
    <Cell ss:Index="5"><Data ss:Type="String">猜表哥</Data></Cell>
    <Cell ss:Index="9"><Data ss:Type="String">欧米伽</Data></Cell>
   </Row>
   <Row ss:Index="240">
    <Cell ss:Index="5"><Data ss:Type="String">猜包包</Data></Cell>
    <Cell ss:Index="9"><Data ss:Type="String">LV</Data></Cell>
   </Row>
   <Row>
    <Cell ss:Index="5"><Data ss:Type="String">猜包包</Data></Cell>
    <Cell ss:Index="9"><Data ss:Type="String">香奈儿</Data></Cell>
   </Row>
   <Row>
    <Cell ss:Index="5"><Data ss:Type="String">猜包包</Data></Cell>
    <Cell ss:Index="9"><Data ss:Type="String">GUCCI</Data></Cell>
   </Row>
   <Row>
    <Cell ss:Index="5"><Data ss:Type="String">猜包包</Data></Cell>
    <Cell ss:Index="9"><Data ss:Type="String">POLO</Data></Cell>
   </Row>
   <Row>
    <Cell ss:Index="5"><Data ss:Type="String">猜包包</Data></Cell>
    <Cell ss:Index="9"><Data ss:Type="String">PRADA</Data></Cell>
   </Row>
   <Row>
    <Cell ss:Index="5"><Data ss:Type="String">猜包包</Data></Cell>
    <Cell ss:Index="9"><Data ss:Type="String">coach</Data></Cell>
   </Row>
   <Row>
    <Cell ss:Index="5"><Data ss:Type="String">猜包包</Data></Cell>
    <Cell ss:Index="9"><Data ss:Type="String">爱马仕</Data></Cell>
   </Row>
   <Row>
    <Cell ss:Index="5"><Data ss:Type="String">猜包包</Data></Cell>
    <Cell ss:Index="9"><Data ss:Type="String">bally</Data></Cell>
   </Row>
   <Row>
    <Cell ss:Index="5"><Data ss:Type="String">猜包包</Data></Cell>
    <Cell ss:Index="9"><Data ss:Type="String">burberry</Data></Cell>
   </Row>
   <Row>
    <Cell ss:Index="5"><Data ss:Type="String">猜包包</Data></Cell>
    <Cell ss:Index="9"><Data ss:Type="String">芬迪</Data></Cell>
   </Row>
   <Row>
    <Cell ss:Index="5"><Data ss:Type="String">猜包包</Data></Cell>
    <Cell ss:Index="9"><Data ss:Type="String">Diro</Data></Cell>
   </Row>
   <Row>
    <Cell ss:Index="5"><Data ss:Type="String">猜包包</Data></Cell>
    <Cell ss:Index="9"><Data ss:Type="String">miumiu</Data></Cell>
   </Row>
   <Row>
    <Cell ss:Index="5"><Data ss:Type="String">猜包包</Data></Cell>
    <Cell ss:Index="9"><Data ss:Type="String">菲拉格慕</Data></Cell>
   </Row>
   <Row>
    <Cell ss:Index="5"><Data ss:Type="String">猜包包</Data></Cell>
    <Cell ss:Index="9"><Data ss:Type="String">阿玛尼</Data></Cell>
   </Row>
   <Row ss:Index="256">
    <Cell ss:Index="5"><Data ss:Type="String">特色音</Data></Cell>
    <Cell ss:Index="9"><Data ss:Type="String">郭德纲</Data></Cell>
   </Row>
   <Row>
    <Cell ss:Index="5"><Data ss:Type="String">特色音</Data></Cell>
    <Cell ss:Index="9"><Data ss:Type="String">华少</Data></Cell>
   </Row>
   <Row>
    <Cell ss:Index="5"><Data ss:Type="String">特色音</Data></Cell>
    <Cell ss:Index="9"><Data ss:Type="String">曾志伟</Data></Cell>
   </Row>
   <Row>
    <Cell ss:Index="5"><Data ss:Type="String">特色音</Data></Cell>
    <Cell ss:Index="9"><Data ss:Type="String">赵忠祥</Data></Cell>
   </Row>
   <Row>
    <Cell ss:Index="5"><Data ss:Type="String">特色音</Data></Cell>
    <Cell ss:Index="9"><Data ss:Type="String">林志玲</Data></Cell>
   </Row>
   <Row>
    <Cell ss:Index="5"><Data ss:Type="String">特色音</Data></Cell>
    <Cell ss:Index="9"><Data ss:Type="String">周杰伦</Data></Cell>
   </Row>
   <Row>
    <Cell ss:Index="5"><Data ss:Type="String">特色音</Data></Cell>
   </Row>
   <Row>
    <Cell ss:Index="5"><Data ss:Type="String">特色音</Data></Cell>
   </Row>
   <Row>
    <Cell ss:Index="5"><Data ss:Type="String">特色音</Data></Cell>
   </Row>
   <Row>
    <Cell ss:Index="5"><Data ss:Type="String">特色音</Data></Cell>
   </Row>
   <Row>
    <Cell ss:Index="5"><Data ss:Type="String">特色音</Data></Cell>
   </Row>
   <Row>
    <Cell ss:Index="5"><Data ss:Type="String">特色音</Data></Cell>
   </Row>
   <Row>
    <Cell ss:Index="4"><Data ss:Type="String">许三多</Data></Cell>
    <Cell><Data ss:Type="String">特色音</Data></Cell>
    <Cell ss:Index="9"><Data ss:Type="String">许三多</Data></Cell>
   </Row>
   <Row>
    <Cell ss:Index="4"><Data ss:Type="String">韦小宝</Data></Cell>
    <Cell><Data ss:Type="String">特色音</Data></Cell>
    <Cell ss:Index="9"><Data ss:Type="String">韦小宝</Data></Cell>
   </Row>
   <Row ss:Height="24">
    <Cell ss:Index="4"><Data ss:Type="String">好男人就是我，我就是曾小贤</Data></Cell>
    <Cell><Data ss:Type="String">特色音</Data></Cell>
    <Cell ss:Index="9"><Data ss:Type="String">曾小贤</Data></Cell>
   </Row>
   <Row>
    <Cell ss:Index="4"><Data ss:Type="String">元芳你怎么看</Data></Cell>
    <Cell><Data ss:Type="String">特色音</Data></Cell>
    <Cell ss:Index="9"><Data ss:Type="String">狄仁杰</Data></Cell>
   </Row>
   <Row ss:Index="274">
    <Cell ss:Index="5"><Data ss:Type="String">动漫游戏</Data></Cell>
    <Cell ss:Index="9"><Data ss:Type="String">超人</Data></Cell>
   </Row>
   <Row>
    <Cell ss:Index="5"><Data ss:Type="String">动漫游戏</Data></Cell>
    <Cell ss:Index="9"><Data ss:Type="String">蜘蛛侠</Data></Cell>
   </Row>
   <Row>
    <Cell ss:Index="5"><Data ss:Type="String">动漫游戏</Data></Cell>
    <Cell ss:Index="9"><Data ss:Type="String">蝙蝠侠</Data></Cell>
   </Row>
   <Row>
    <Cell ss:Index="5"><Data ss:Type="String">动漫游戏</Data></Cell>
    <Cell ss:Index="9"><Data ss:Type="String">绿巨人</Data></Cell>
   </Row>
   <Row>
    <Cell ss:Index="5"><Data ss:Type="String">动漫游戏</Data></Cell>
    <Cell ss:Index="9"><Data ss:Type="String">绿灯侠</Data></Cell>
   </Row>
   <Row>
    <Cell ss:Index="5"><Data ss:Type="String">动漫游戏</Data></Cell>
    <Cell ss:Index="9"><Data ss:Type="String">闪电侠</Data></Cell>
   </Row>
   <Row>
    <Cell ss:Index="5"><Data ss:Type="String">动漫游戏</Data></Cell>
    <Cell ss:Index="9"><Data ss:Type="String">美国队长</Data></Cell>
   </Row>
   <Row>
    <Cell ss:Index="5"><Data ss:Type="String">动漫游戏</Data></Cell>
    <Cell ss:Index="9"><Data ss:Type="String">钢铁侠</Data></Cell>
   </Row>
   <Row>
    <Cell ss:Index="5"><Data ss:Type="String">动漫游戏</Data></Cell>
    <Cell ss:Index="9"><Data ss:Type="String">孙悟空</Data></Cell>
   </Row>
   <Row>
    <Cell ss:Index="5"><Data ss:Type="String">动漫游戏</Data></Cell>
    <Cell ss:Index="9"><Data ss:Type="String">奥特曼</Data></Cell>
   </Row>
   <Row>
    <Cell ss:Index="5"><Data ss:Type="String">动漫游戏</Data></Cell>
   </Row>
   <Row>
    <Cell ss:Index="5"><Data ss:Type="String">动漫游戏</Data></Cell>
   </Row>
   <Row>
    <Cell ss:Index="5"><Data ss:Type="String">动漫游戏</Data></Cell>
   </Row>
   <Row>
    <Cell ss:Index="5"><Data ss:Type="String">动漫游戏</Data></Cell>
   </Row>
  </Table>
  <WorksheetOptions xmlns="urn:schemas-microsoft-com:office:excel">
   <PageSetup>
    <Header x:Margin="0.3"/>
    <Footer x:Margin="0.3"/>
    <PageMargins x:Bottom="0.75" x:Left="0.7" x:Right="0.7" x:Top="0.75"/>
   </PageSetup>
   <Print>
    <ValidPrinterInfo/>
    <PaperSizeIndex>9</PaperSizeIndex>
    <HorizontalResolution>600</HorizontalResolution>
    <VerticalResolution>600</VerticalResolution>
   </Print>
   <PageLayoutZoom>0</PageLayoutZoom>
   <Selected/>
   <TopRowVisible>259</TopRowVisible>
   <LeftColumnVisible>3</LeftColumnVisible>
   <Panes>
    <Pane>
     <Number>3</Number>
     <ActiveRow>297</ActiveRow>
     <ActiveCol>12</ActiveCol>
    </Pane>
   </Panes>
   <ProtectObjects>False</ProtectObjects>
   <ProtectScenarios>False</ProtectScenarios>
  </WorksheetOptions>
 </Worksheet>
 <Worksheet ss:Name="Sheet2">
  <Table ss:ExpandedColumnCount="1" ss:ExpandedRowCount="1" x:FullColumns="1"
   x:FullRows="1" ss:DefaultColumnWidth="61" ss:DefaultRowHeight="12">
  </Table>
  <WorksheetOptions xmlns="urn:schemas-microsoft-com:office:excel">
   <PageSetup>
    <Header x:Margin="0.3"/>
    <Footer x:Margin="0.3"/>
    <PageMargins x:Bottom="0.75" x:Left="0.7" x:Right="0.7" x:Top="0.75"/>
   </PageSetup>
   <PageLayoutZoom>0</PageLayoutZoom>
   <ProtectObjects>False</ProtectObjects>
   <ProtectScenarios>False</ProtectScenarios>
  </WorksheetOptions>
 </Worksheet>
 <Worksheet ss:Name="Sheet3">
  <Table ss:ExpandedColumnCount="1" ss:ExpandedRowCount="1" x:FullColumns="1"
   x:FullRows="1" ss:DefaultColumnWidth="61" ss:DefaultRowHeight="12">
  </Table>
  <WorksheetOptions xmlns="urn:schemas-microsoft-com:office:excel">
   <PageSetup>
    <Header x:Margin="0.3"/>
    <Footer x:Margin="0.3"/>
    <PageMargins x:Bottom="0.75" x:Left="0.7" x:Right="0.7" x:Top="0.75"/>
   </PageSetup>
   <PageLayoutZoom>0</PageLayoutZoom>
   <ProtectObjects>False</ProtectObjects>
   <ProtectScenarios>False</ProtectScenarios>
  </WorksheetOptions>
 </Worksheet>
</Workbook>
